covertreec.cpython-38-x86_64-linux-gnu.so
sccc.cpython-38-x86_64-linux-gnu.so
sgtreec.cpython-38-x86_64-linux-gnu.so
llamac.cpython-38-x86_64-linux-gnu.so
graphgrove-0.0.11.dist-info/WHEEL
graphgrove-0.0.11.dist-info/NOTICE
graphgrove-0.0.11.dist-info/top_level.txt
graphgrove-0.0.11.dist-info/LICENSE
graphgrove-0.0.11.dist-info/RECORD
graphgrove-0.0.11.dist-info/METADATA
graphgrove-0.0.11.dist-info/AUTHORS
graphgrove/vec_scc.py
graphgrove/covertree.py
graphgrove/__init__.py
graphgrove/sgtree.py
graphgrove/scc.py
graphgrove/llama.py
graphgrove/graph_builder.py
