Metadata-Version: 2.1
Name: graphgrove
Version: 0.0.11
Summary: Building flat, tree, and DAG structured clusterings.
Home-page: https://github.com/nmonath/graphgrove
Author: Nicholas Monath
Author-email: nmonath@cs.umass.edu
License: UNKNOWN
Project-URL: Bug Tracker, https://github.com/nmonath/graphgrove/issues
Platform: UNKNOWN
Classifier: Programming Language :: Python :: 3
Requires-Python: >=3.6
License-File: LICENSE
License-File: NOTICE
License-File: AUTHORS
Requires-Dist: numpy
Requires-Dist: scipy
Requires-Dist: tqdm
Requires-Dist: absl-py
